libtakiyasha/VERSION
libtakiyasha/__init__.py
libtakiyasha/_keyutils.py
libtakiyasha/_miscutils.py
libtakiyasha/_prototypes.py
libtakiyasha/_stdciphers.py
libtakiyasha/_typeutils.py
libtakiyasha/exceptions.py
libtakiyasha/ncm.py
libtakiyasha/pkgmetadata.py
libtakiyasha/typedefs.py
libtakiyasha/warns.py
libtakiyasha/_binaries/ncm/empty.flac
libtakiyasha/_binaries/qmc/_qmcconsts/Key256MappingData
libtakiyasha/kgmvpr/__init__.py
libtakiyasha/kgmvpr/_kgmvprdataciphers.py
libtakiyasha/kwm/__init__.py
libtakiyasha/kwm/_kwmdataciphers.py
libtakiyasha/qmc/__init__.py
libtakiyasha/qmc/_qmcconsts.py
libtakiyasha/qmc/_qmcdataciphers.py
libtakiyasha/qmc/_qmckeyciphers.py
libtakiyasha-2.1.1.post1.dist-info/LICENSE
libtakiyasha-2.1.1.post1.dist-info/METADATA
libtakiyasha-2.1.1.post1.dist-info/WHEEL
libtakiyasha-2.1.1.post1.dist-info/top_level.txt
libtakiyasha-2.1.1.post1.dist-info/RECORD
