Metadata-Version: 2.1
Name: libtakiyasha
Version: 2.1.1.post1
Summary: 多种加密方案的 Python 实现
Author: nukemiko
License: MIT License
Project-URL: Homepage, https://github.com/nukemiko/libtakiyasha
Project-URL: Documentation, https://github.com/nukemiko/libtakiyasha/wiki
Project-URL: Bug Tracker, https://github.com/nukemiko/libtakiyasha/issues
Project-URL: Releases, https://github.com/nukemiko/libtakiyasha/releases
Keywords: unlock,music,audio,qmc,ncm,mflac,mgg,netease,163,qqmusic
Classifier: License :: OSI Approved :: MIT License
Classifier: Operating System :: OS Independent
Classifier: Topic :: Multimedia :: Sound/Audio
Classifier: Programming Language :: Python :: 3
Classifier: Programming Language :: Python :: 3 :: Only
Classifier: Programming Language :: Python :: 3.8
Classifier: Programming Language :: Python :: 3.9
Classifier: Programming Language :: Python :: 3.10
Requires-Python: >=3.8
License-File: LICENSE
Requires-Dist: pyaes
Requires-Dist: mutagen
